onsagernet/__init__.py
onsagernet/_activations.py
onsagernet/_layers.py
onsagernet/_losses.py
onsagernet/_utils.py
onsagernet/dynamics.py
onsagernet/models.py
onsagernet/trainers.py
onsagernet/transformations.py
onsagernet-0.1.3.dist-info/METADATA
onsagernet-0.1.3.dist-info/WHEEL
onsagernet-0.1.3.dist-info/RECORD
