Metadata-Version: 2.1
Name: onsagernet
Version: 0.1.3
Summary: 
Author: Qianxiao Li
Requires-Python: >=3.12,<4.0
Classifier: Programming Language :: Python :: 3
Classifier: Programming Language :: Python :: 3.12
Requires-Dist: datasets (>=3.0.0,<4.0.0)
Requires-Dist: equinox (>=0.11.5,<0.12.0)
Requires-Dist: optax (>=0.2.3,<0.3.0)
Requires-Dist: pdoc (>=14.7.0,<15.0.0)
Requires-Dist: tqdm (>=4.66.5,<5.0.0)
